{
  "Records": [
    {
      "eventID": "c4ca4238a0b923820dcc509a6f75849b",
      "eventName": "INSERT",
      "eventVersion": "1.1",
      "eventSource": "aws:dynamodb",
      "awsRegion": "us-east-1",
      "dynamodb": {
        "Keys": {
          "project_id": "21c1d15d-ad64-4bd0-ab09-1f4007353536"
        },
        "NewImage": {
          "project_id": "21c1d15d-ad64-4bd0-ab09-1f4007353536",
          "name": "hogehoge",
          "updated_by": "23d17225-ad00-424b-afa4-068c96c49c41",
          "updated_at": "2019-06-24T11:24:23.289809"
        },
        "ApproximateCreationDateTime": 1428537600,
        "SequenceNumber": "4421584500000000017450439091",
        "SizeBytes": 26,
        "StreamViewType": "NEW_AND_OLD_IMAGES"
      },
      "eventSourceARN": "arn:aws:dynamodb:us-east-1:123456789012:table/Projects/stream/2015-06-27T00:48:05.899"
    },
    {
      "eventID": "c81e728d9d4c2f636f067f89cc14862c",
      "eventName": "MODIFY",
      "eventVersion": "1.1",
      "eventSource": "aws:dynamodb",
      "awsRegion": "us-east-1",
      "dynamodb": {
        "Keys": {
          "project_id": "21c1d15d-ad64-4bd0-ab09-1f4007353536"
        },
        "NewImage": {
          "project_id": "21c1d15d-ad64-4bd0-ab09-1f4007353536",
          "name": "hogehoge",
          "updated_by": "23d17225-ad00-424b-afa4-068c96c49c41",
          "updated_at": "2019-06-24T11:24:23.289809"
        },
        "OldImage": {
          "project_id": "21c1d15d-ad64-4bd0-ab09-1f4007353536",
          "name": "old_foobar",
          "updated_by": "23d17225-ad00-424b-afa4-068c96c49c41",
          "updated_at": "2019-06-24T11:24:23.289809"
        },
        "ApproximateCreationDateTime": 1428537600,
        "SequenceNumber": "4421584500000000017450439092",
        "SizeBytes": 59,
        "StreamViewType": "NEW_AND_OLD_IMAGES"
      },
      "eventSourceARN": "arn:aws:dynamodb:us-east-1:123456789012:table/Places/stream/2015-06-27T00:48:05.899"
    },
    {
      "eventID": "eccbc87e4b5ce2fe28308fd9f2a7baf3",
      "eventName": "REMOVE",
      "eventVersion": "1.1",
      "eventSource": "aws:dynamodb",
      "awsRegion": "us-east-1",
      "dynamodb": {
        "Keys": {
          "project_id": "21c1d15d-ad64-4bd0-ab09-1f4007353536"
        },
        "OldImage": {
          "project_id": "21c1d15d-ad64-4bd0-ab09-1f4007353536",
          "name": "old_foobar",
          "updated_by": "23d17225-ad00-424b-afa4-068c96c49c41",
          "updated_at": "2019-06-24T11:24:23.289809",
          "photos": {
            "adopt": {
              "before": "hogehoge",
              "after": "foobar"
            }
          }
        },
        "ApproximateCreationDateTime": 1428537600,
        "SequenceNumber": "4421584500000000017450439093",
        "SizeBytes": 38,
        "StreamViewType": "NEW_AND_OLD_IMAGES"
      },
      "eventSourceARN": "arn:aws:dynamodb:us-east-1:123456789012:table/Targets/stream/2015-06-27T00:48:05.899"
    }
  ]
}
